WinDeft-1.0.0.dist-info/DESCRIPTION.rst
WinDeft-1.0.0.dist-info/METADATA
WinDeft-1.0.0.dist-info/RECORD
WinDeft-1.0.0.dist-info/WHEEL
WinDeft-1.0.0.dist-info/entry_points.txt
WinDeft-1.0.0.dist-info/metadata.json
WinDeft-1.0.0.dist-info/top_level.txt
windeft/__init__.py
