Metadata-Version: 2.0
Name: WinDeft
Version: 1.0.0
Summary: Windows Defender Tester.
Home-page: https://github.com/hadi16/windeft
Author: Alex Hadi
Author-email: UNKNOWN
License: Apache License, Version 2.0
Platform: UNKNOWN
Requires-Python: ==2.7.*
Requires-Dist: click
